COPYING
COPYING.lesser
MANIFEST.in
NOTICE
README.md
requirements.txt
setup.py
compiler/__init__.py
compiler/api/__init__.py
compiler/api/compiler.py
compiler/api/source/auth_key.tl
compiler/api/source/main_api.tl
compiler/api/source/sys_msgs.tl
compiler/api/template/combinator.txt
compiler/api/template/type.txt
compiler/docs/__init__.py
compiler/docs/compiler.py
compiler/docs/template/page.txt
compiler/docs/template/toctree.txt
compiler/errors/__init__.py
compiler/errors/compiler.py
compiler/errors/sort.py
compiler/errors/source/303_SEE_OTHER.tsv
compiler/errors/source/400_BAD_REQUEST.tsv
compiler/errors/source/401_UNAUTHORIZED.tsv
compiler/errors/source/403_FORBIDDEN.tsv
compiler/errors/source/406_NOT_ACCEPTABLE.tsv
compiler/errors/source/420_FLOOD.tsv
compiler/errors/source/500_INTERNAL_SERVER_ERROR.tsv
compiler/errors/source/503_SERVICE_UNAVAILABLE.tsv
compiler/errors/template/class.txt
compiler/errors/template/sub_class.txt
noelgram/__init__.py
noelgram/client.py
noelgram/dispatcher.py
noelgram/emoji.py
noelgram/file_id.py
noelgram/filters.py
noelgram/mime_types.py
noelgram/py.typed
noelgram/sync.py
noelgram/utils.py
noelgram1.egg-info/PKG-INFO
noelgram1.egg-info/SOURCES.txt
noelgram1.egg-info/dependency_links.txt
noelgram1.egg-info/not-zip-safe
noelgram1.egg-info/requires.txt
noelgram1.egg-info/top_level.txt
noelgram/connection/__init__.py
noelgram/connection/connection.py
noelgram/connection/transport/__init__.py
noelgram/connection/transport/tcp/__init__.py
noelgram/connection/transport/tcp/tcp.py
noelgram/connection/transport/tcp/tcp_abridged.py
noelgram/connection/transport/tcp/tcp_abridged_o.py
noelgram/connection/transport/tcp/tcp_full.py
noelgram/connection/transport/tcp/tcp_intermediate.py
noelgram/connection/transport/tcp/tcp_intermediate_o.py
noelgram/crypto/__init__.py
noelgram/crypto/aes.py
noelgram/crypto/mtproto.py
noelgram/crypto/prime.py
noelgram/crypto/rsa.py
noelgram/enums/__init__.py
noelgram/enums/auto_name.py
noelgram/enums/chat_action.py
noelgram/enums/chat_event_action.py
noelgram/enums/chat_member_status.py
noelgram/enums/chat_members_filter.py
noelgram/enums/chat_type.py
noelgram/enums/message_entity_type.py
